Workbook

Sheet Cover
A1: CLISONIX INVESTOR MODEL — ADVANCED ANALYTICS
A3: Board-grade financial model with scenarios, sensitivities, funnel stats, and monthly dynamics
A5: Key features
A6: • 3-year P&L with linked assumptions
A7: • Monthly 2026 forecast (users, MRR, churn, runway)
A8: • Scenario analysis (Bear/Base/Bull)
A9: • Sensitivity matrix (conversion vs churn)
A10: • Detailed unit economics and payback
A11: • Infrastructure efficiency statistics
A14: Primary input sheet: Assumptions
A15: Generated by: investor-pack/build_investor_excel.py

Sheet Assumptions
A1: Model Assumptions
A3: Input | B3: 2026 | C3: 2027 | D3: 2028
A4: Total Users | B4: 15420 | C4: 45720 | D4: 121800
A5: Paid Users | B5: 600 | C5: 3013 | D5: 8673
A6: Average ARPU (monthly) | B6: 16.8 | C6: 25.4 | D6: 32.8
A7: Monthly Churn | B7: 0.025 | C7: 0.022 | D7: 0.018
A8: Free→Paid Conversion | B8: 0.039 | C8: 0.052 | D8: 0.071
A9: CAC | B9: 86 | C9: 64 | D9: 47
A10: Infrastructure Monthly | B10: 917 | C10: 1489 | D10: 2098
A11: Monthly OPEX | B11: 58417 | C11: 90823 | D11: 151765
A12: Monthly Growth (users) | B12: 0.15 | C12: 0.11 | D12: 0.09
A15: Scenario multipliers
A16: Scenario | B16: Revenue Multiplier | C16: Cost Multiplier
A17: Bear | B17: 0.8 | C17: 1.1
A18: Base | B18: 1 | C18: 1
A19: Bull | B19: 1.2 | C19: 0.95

Sheet Revenue_Model
A1: Plan | B1: Price/Month | C1: Users 2026 | D1: Users 2027 | E1: Users 2028 | F1: Revenue 2026 | G1: Revenue 2027 | H1: Revenue 2028 | I1: % of 2028
A2: Basic | B2: 0 | C2: 15000 | D2: 45000 | E2: 120000 | F2: =B2*C2*12 | G2: =B2*D2*12 | H2: =B2*E2*12 | I2: =IF($H$9=0,0,H2/$H$9)
A3: Pro | B3: 29 | C3: 420 | D3: 2600 | E3: 8300 | F3: =B3*C3*12 | G3: =B3*D3*12 | H3: =B3*E3*12 | I3: =IF($H$9=0,0,H3/$H$9)
A4: Research | B4: 99 | C4: 85 | D4: 370 | E4: 1250 | F4: =B4*C4*12 | G4: =B4*D4*12 | H4: =B4*E4*12 | I4: =IF($H$9=0,0,H4/$H$9)
A5: Enterprise | B5: 499 | C5: 6 | D5: 20 | E5: 48 | F5: =B5*C5*12 | G5: =B5*D5*12 | H5: =B5*E5*12 | I5: =IF($H$9=0,0,H5/$H$9)
A6: API/Developer | B6: 299 | C6: 3 | D6: 18 | E6: 55 | F6: =B6*C6*12 | G6: =B6*D6*12 | H6: =B6*E6*12 | I6: =IF($H$9=0,0,H6/$H$9)
A7: Educational | B7: 199 | C7: 8 | D7: 25 | E7: 70 | F7: =B7*C7*12 | G7: =B7*D7*12 | H7: =B7*E7*12 | I7: =IF($H$9=0,0,H7/$H$9)
I8: =IF($H$9=0,0,H8/$H$9)
A9: TOTAL | F9: =SUM(F2:F8) | G9: =SUM(G2:G8) | H9: =SUM(H2:H8)

Sheet Infrastructure
A1: Component | B1: Monthly | C1: Yearly 2026 | D1: Yearly 2027 | E1: Yearly 2028 | F1: Unit
A2: Hetzner GPU Server (RTX 5090) | B2: 509 | C2: =B2*12 | D2: =B2*12*2 | E2: =B2*12*3 | F2: Core compute
A3: Storage + Backups | B3: 258 | C3: =B3*12 | D3: =B3*12 | E3: =B3*12 | F3: Data durability
A4: DDoS/Edge Security | B4: 50 | C4: =B4*12 | D4: =B4*12 | E4: =B4*12 | F4: Security
A5: Monitoring | B5: 20 | C5: =B5*12 | D5: =B5*12 | E5: =B5*12 | F5: Observability
A6: Bandwidth Reserve | B6: 80 | C6: =B6*12 | D6: =B6*12 | E6: =B6*12 | F6: Network
A8: TOTAL | B8: =SUM(B2:B6) | C8: =SUM(C2:C6) | D8: =SUM(D2:D6) | E8: =SUM(E2:E6)
A10: Users | B10: =Assumptions!B4 | C10: =Assumptions!C4 | D10: =Assumptions!D4
A11: Infra Cost per User | B11: =IF(B10=0,0,C8/B10) | C11: =IF(C10=0,0,D8/C10) | D11: =IF(D10=0,0,E8/D10)

Sheet OPEX
A1: Category | B1: Monthly 2026 | C1: Yearly 2026 | D1: Yearly 2027 | E1: Yearly 2028 | F1: % 2026
A2: R&D & Development | B2: 28000 | C2: =B2*12 | D2: 480000 | E2: 720000 | F2: =IF($C$9=0,0,C2/$C$9)
A3: Marketing & Sales | B3: 18500 | C3: =B3*12 | D3: 400000 | E3: 800000 | F3: =IF($C$9=0,0,C3/$C$9)
A4: Operations | B4: 6500 | C4: =B4*12 | D4: 120000 | E4: 180000 | F4: =IF($C$9=0,0,C4/$C$9)
A5: Legal & Admin | B5: 3000 | C5: =B5*12 | D5: 48000 | E5: 60000 | F5: =IF($C$9=0,0,C5/$C$9)
A6: Office & Misc | B6: 1500 | C6: =B6*12 | D6: 24000 | E6: 36000 | F6: =IF($C$9=0,0,C6/$C$9)
A7: Infrastructure | B7: =Infrastructure!B8 | C7: =Infrastructure!C8 | D7: =Infrastructure!D8 | E7: =Infrastructure!E8 | F7: =IF($C$9=0,0,C7/$C$9)
A9: TOTAL | B9: =SUM(B2:B7) | C9: =SUM(C2:C7) | D9: =SUM(D2:D7) | E9: =SUM(E2:E7)

Sheet PnL_3Y
A1: Metric | B1: 2026 | C1: 2027 | D1: 2028 | E1: YoY 2027 | F1: YoY 2028
A2: Total Revenue | B2: =Revenue_Model!F9 | C2: =Revenue_Model!G9 | D2: =Revenue_Model!H9 | E2: =IF(B2=0,0,C2/B2-1) | F2: =IF(C2=0,0,D2/C2-1)
A3: Total Expenses | B3: =OPEX!C9 | C3: =OPEX!D9 | D3: =OPEX!E9 | E3: =IF(B3=0,0,C3/B3-1) | F3: =IF(C3=0,0,D3/C3-1)
A4: EBITDA | B4: =B2-B3 | C4: =C2-C3 | D4: =D2-D3 | E4: =IF(ABS(B4)<1,0,C4/B4-1) | F4: =IF(ABS(C4)<1,0,D4/C4-1)
A5: EBITDA Margin | B5: =IF(B2=0,0,B4/B2) | C5: =IF(C2=0,0,C4/C2) | D5: =IF(D2=0,0,D4/D2)

Sheet Monthly_Forecast_2026
A1: Month | B1: Users | C1: Paid Users | D1: New Paid | E1: Churned Paid | F1: MRR | G1: Revenue | H1: COGS(Infra) | I1: Gross Profit | J1: Burn | K1: Runway (months)
A2: Jan | B2: =Assumptions!B4 | C2: =Assumptions!B5 | D2: =C2*Assumptions!B8 | E2: =C2*Assumptions!B7 | F2: =C2*Assumptions!B6 | G2: =F2 | H2: =Infrastructure!B8 | I2: =G2-H2 | J2: =OPEX!B9-I2 | K2: =IF(J2<=0,999,600000/J2)
A3: Feb | B3: =B2*(1+Assumptions!B12) | C3: =C2+D2-E2 | D3: =B3*Assumptions!B8 | E3: =C2*Assumptions!B7 | F3: =C3*Assumptions!B6 | G3: =F3 | H3: =Infrastructure!B8 | I3: =G3-H3 | J3: =OPEX!B9-I3 | K3: =IF(J3<=0,999,600000/J3)
A4: Mar | B4: =B3*(1+Assumptions!B12) | C4: =C3+D3-E3 | D4: =B4*Assumptions!B8 | E4: =C3*Assumptions!B7 | F4: =C4*Assumptions!B6 | G4: =F4 | H4: =Infrastructure!B8 | I4: =G4-H4 | J4: =OPEX!B9-I4 | K4: =IF(J4<=0,999,600000/J4)
A5: Apr | B5: =B4*(1+Assumptions!B12) | C5: =C4+D4-E4 | D5: =B5*Assumptions!B8 | E5: =C4*Assumptions!B7 | F5: =C5*Assumptions!B6 | G5: =F5 | H5: =Infrastructure!B8 | I5: =G5-H5 | J5: =OPEX!B9-I5 | K5: =IF(J5<=0,999,600000/J5)
A6: May | B6: =B5*(1+Assumptions!B12) | C6: =C5+D5-E5 | D6: =B6*Assumptions!B8 | E6: =C5*Assumptions!B7 | F6: =C6*Assumptions!B6 | G6: =F6 | H6: =Infrastructure!B8 | I6: =G6-H6 | J6: =OPEX!B9-I6 | K6: =IF(J6<=0,999,600000/J6)
A7: Jun | B7: =B6*(1+Assumptions!B12) | C7: =C6+D6-E6 | D7: =B7*Assumptions!B8 | E7: =C6*Assumptions!B7 | F7: =C7*Assumptions!B6 | G7: =F7 | H7: =Infrastructure!B8 | I7: =G7-H7 | J7: =OPEX!B9-I7 | K7: =IF(J7<=0,999,600000/J7)
A8: Jul | B8: =B7*(1+Assumptions!B12) | C8: =C7+D7-E7 | D8: =B8*Assumptions!B8 | E8: =C7*Assumptions!B7 | F8: =C8*Assumptions!B6 | G8: =F8 | H8: =Infrastructure!B8 | I8: =G8-H8 | J8: =OPEX!B9-I8 | K8: =IF(J8<=0,999,600000/J8)
A9: Aug | B9: =B8*(1+Assumptions!B12) | C9: =C8+D8-E8 | D9: =B9*Assumptions!B8 | E9: =C8*Assumptions!B7 | F9: =C9*Assumptions!B6 | G9: =F9 | H9: =Infrastructure!B8 | I9: =G9-H9 | J9: =OPEX!B9-I9 | K9: =IF(J9<=0,999,600000/J9)
A10: Sep | B10: =B9*(1+Assumptions!B12) | C10: =C9+D9-E9 | D10: =B10*Assumptions!B8 | E10: =C9*Assumptions!B7 | F10: =C10*Assumptions!B6 | G10: =F10 | H10: =Infrastructure!B8 | I10: =G10-H10 | J10: =OPEX!B9-I10 | K10: =IF(J10<=0,999,600000/J10)
A11: Oct | B11: =B10*(1+Assumptions!B12) | C11: =C10+D10-E10 | D11: =B11*Assumptions!B8 | E11: =C10*Assumptions!B7 | F11: =C11*Assumptions!B6 | G11: =F11 | H11: =Infrastructure!B8 | I11: =G11-H11 | J11: =OPEX!B9-I11 | K11: =IF(J11<=0,999,600000/J11)
A12: Nov | B12: =B11*(1+Assumptions!B12) | C12: =C11+D11-E11 | D12: =B12*Assumptions!B8 | E12: =C11*Assumptions!B7 | F12: =C12*Assumptions!B6 | G12: =F12 | H12: =Infrastructure!B8 | I12: =G12-H12 | J12: =OPEX!B9-I12 | K12: =IF(J12<=0,999,600000/J12)
A13: Dec | B13: =B12*(1+Assumptions!B12) | C13: =C12+D12-E12 | D13: =B13*Assumptions!B8 | E13: =C12*Assumptions!B7 | F13: =C13*Assumptions!B6 | G13: =F13 | H13: =Infrastructure!B8 | I13: =G13-H13 | J13: =OPEX!B9-I13 | K13: =IF(J13<=0,999,600000/J13)
A15: Totals | G15: =SUM(G2:G13) | J15: =SUM(J2:J13) | K15: =AVERAGE(K2:K13)

Sheet Scenario_Analysis
A1: Scenario | B1: Revenue 2028 | C1: Expenses 2028 | D1: EBITDA 2028 | E1: EBITDA Margin | F1: Implied Valuation (8x EBITDA)
A2: Bear | B2: =PnL_3Y!D2*Assumptions!B17 | C2: =PnL_3Y!D3*Assumptions!C17 | D2: =B2-C2 | E2: =IF(B2=0,0,D2/B2) | F2: =D2*8
A3: Base | B3: =PnL_3Y!D2*Assumptions!B18 | C3: =PnL_3Y!D3*Assumptions!C18 | D3: =B3-C3 | E3: =IF(B3=0,0,D3/B3) | F3: =D3*8
A4: Bull | B4: =PnL_3Y!D2*Assumptions!B19 | C4: =PnL_3Y!D3*Assumptions!C19 | D4: =B4-C4 | E4: =IF(B4=0,0,D4/B4) | F4: =D4*8

Sheet Sensitivity
A1: Sensitivity Matrix: LTV/CAC by Conversion and Churn
A3: Conv/Churn | B3: 0.015 | C3: 0.02 | D3: 0.025 | E3: 0.03 | F3: 0.035
A4: 0.03 | B4: =((Assumptions!B6*0.85)/B3)/(Assumptions!B10/400) | C4: =((Assumptions!B6*0.85)/C3)/(Assumptions!B10/400) | D4: =((Assumptions!B6*0.85)/D3)/(Assumptions!B10/400) | E4: =((Assumptions!B6*0.85)/E3)/(Assumptions!B10/400) | F4: =((Assumptions!B6*0.85)/F3)/(Assumptions!B10/400)
A5: 0.04 | B5: =((Assumptions!B6*0.85)/B3)/(Assumptions!B10/500) | C5: =((Assumptions!B6*0.85)/C3)/(Assumptions!B10/500) | D5: =((Assumptions!B6*0.85)/D3)/(Assumptions!B10/500) | E5: =((Assumptions!B6*0.85)/E3)/(Assumptions!B10/500) | F5: =((Assumptions!B6*0.85)/F3)/(Assumptions!B10/500)
A6: 0.05 | B6: =((Assumptions!B6*0.85)/B3)/(Assumptions!B10/600) | C6: =((Assumptions!B6*0.85)/C3)/(Assumptions!B10/600) | D6: =((Assumptions!B6*0.85)/D3)/(Assumptions!B10/600) | E6: =((Assumptions!B6*0.85)/E3)/(Assumptions!B10/600) | F6: =((Assumptions!B6*0.85)/F3)/(Assumptions!B10/600)
A7: 0.06 | B7: =((Assumptions!B6*0.85)/B3)/(Assumptions!B10/700) | C7: =((Assumptions!B6*0.85)/C3)/(Assumptions!B10/700) | D7: =((Assumptions!B6*0.85)/D3)/(Assumptions!B10/700) | E7: =((Assumptions!B6*0.85)/E3)/(Assumptions!B10/700) | F7: =((Assumptions!B6*0.85)/F3)/(Assumptions!B10/700)
A8: 0.07 | B8: =((Assumptions!B6*0.85)/B3)/(Assumptions!B10/800) | C8: =((Assumptions!B6*0.85)/C3)/(Assumptions!B10/800) | D8: =((Assumptions!B6*0.85)/D3)/(Assumptions!B10/800) | E8: =((Assumptions!B6*0.85)/E3)/(Assumptions!B10/800) | F8: =((Assumptions!B6*0.85)/F3)/(Assumptions!B10/800)

Sheet Unit_Economics
A1: Metric | B1: 2026 | C1: 2027 | D1: 2028 | E1: Interpretation
A2: CAC | B2: =Assumptions!B10 | C2: =Assumptions!C10 | D2: =Assumptions!D10 | E2: Marketing cost to acquire one paid user
A3: ARPU Monthly | B3: =Assumptions!B6 | C3: =Assumptions!C6 | D3: =Assumptions!D6 | E3: Average paid revenue per month
A4: Gross Margin | B4: =IF(PnL_3Y!B2=0,0,(PnL_3Y!B2-Infrastructure!C8)/PnL_3Y!B2) | C4: =IF(PnL_3Y!C2=0,0,(PnL_3Y!C2-Infrastructure!D8)/PnL_3Y!C2) | D4: =IF(PnL_3Y!D2=0,0,(PnL_3Y!D2-Infrastructure!E8)/PnL_3Y!D2) | E4: Revenue after infra costs
A5: Churn | B5: =Assumptions!B7 | C5: =Assumptions!C7 | D5: =Assumptions!D7 | E5: Monthly paid-user churn
A6: LTV | B6: =IF(B5=0,0,(B3*B4)/B5) | C6: =IF(C5=0,0,(C3*C4)/C5) | D6: =IF(D5=0,0,(D3*D4)/D5) | E6: Lifetime value
A7: LTV/CAC | B7: =IF(B2=0,0,B6/B2) | C7: =IF(C2=0,0,C6/C2) | D7: =IF(D2=0,0,D6/D2) | E7: Unit economics quality
A8: Payback (months) | B8: =IF(B3*B4=0,0,B2/(B3*B4)) | C8: =IF(C3*C4=0,0,C2/(C3*C4)) | D8: =IF(D3*D4=0,0,D2/(D3*D4)) | E8: Time to recover CAC

Sheet Use_of_Funds
A1: Category | B1: Amount | C1: % | E1: Seed Round | F1: 600000
A2: Product Development | B2: 240000 | C2: =B2/$F$1
A3: Marketing Launch | B3: 180000 | C3: =B3/$F$1
A4: Infrastructure | B4: 60000 | C4: =B4/$F$1
A5: Team Expansion | B5: 90000 | C5: =B5/$F$1
A6: Operations & Buffer | B6: 30000 | C6: =B6/$F$1
A8: TOTAL | B8: =SUM(B2:B6) | C8: =SUM(C2:C6)

Sheet KPIs
A1: KPI | B1: Current | C1: Target 2026 | D1: Target 2028 | E1: Status
A2: MRR | B2: 8500 | C2: =Monthly_Forecast_2026!F2 | D2: =PnL_3Y!D2/12 | E2: tracking
A3: Gross Margin | B3: 0.96 | C3: =Unit_Economics!B4 | D3: =Unit_Economics!D4 | E3: good
A4: CAC | B4: 52 | C4: =Unit_Economics!B2 | D4: =Unit_Economics!D2 | E4: improving
A5: LTV | B5: 180 | C5: =Unit_Economics!B6 | D5: =Unit_Economics!D6 | E5: improving
A6: LTV/CAC | B6: 3.5 | C6: =Unit_Economics!B7 | D6: =Unit_Economics!D7 | E6: strong
A7: Runway Months | B7: 6 | C7: =Monthly_Forecast_2026!K15 | D7: =Monthly_Forecast_2026!K15 | E7: monitor

Sheet VC_Benchmark
A1: VC Benchmark — Clisonix vs SaaS Median
A3: Metric | B3: Clisonix 2028 | C3: SaaS Median | D3: Top Quartile | E3: Gap vs Median | F3: Status
A4: Revenue Growth YoY | B4: =PnL_3Y!F2 | C4: 0.9 | D4: 1.4 | E4: =B4-C4 | F4: =IF(B4>=D4,"Top Quartile",IF(B4>=C4,"Above Median","Below Median"))
A5: EBITDA Margin | B5: =PnL_3Y!D5 | C5: 0.15 | D5: 0.3 | E5: =B5-C5 | F5: =IF(B5>=D5,"Top Quartile",IF(B5>=C5,"Above Median","Below Median"))
A6: Gross Margin | B6: =Unit_Economics!D4 | C6: 0.78 | D6: 0.86 | E6: =B6-C6 | F6: =IF(B6>=D6,"Top Quartile",IF(B6>=C6,"Above Median","Below Median"))
A7: LTV/CAC | B7: =Unit_Economics!D7 | C7: 3 | D7: 5 | E7: =B7-C7 | F7: =IF(B7>=D7,"Top Quartile",IF(B7>=C7,"Above Median","Below Median"))
A8: CAC Payback (months) | B8: =Unit_Economics!D8 | C8: 12 | D8: 8 | E8: =C8-B8 | F8: =IF(B8>=D8,"Top Quartile",IF(B8>=C8,"Above Median","Below Median"))
A9: Churn (monthly) | B9: =Unit_Economics!D5 | C9: 0.03 | D9: 0.02 | E9: =C9-B9 | F9: =IF(B9>=D9,"Top Quartile",IF(B9>=C9,"Above Median","Below Median"))
A10: Infra Cost/User | B10: =Infrastructure!D11 | C10: 2.5 | D10: 1.2 | E10: =C10-B10 | F10: =IF(B10>=D10,"Top Quartile",IF(B10>=C10,"Above Median","Below Median"))
A12: Weighted Score | B12: =SUMPRODUCT(B4:B10/C4:C10,{0.15,0.2,0.15,0.2,0.1,0.1,0.1}) | C12: 1 | D12: 1.25
D14: Benchmark Notes
D15: • Medians are directional early-stage SaaS benchmarks.
D16: • Use this sheet for investor narrative, not as audited market data.
D17: • Replace medians/top quartile with sector-specific comps when available.

Sheet Data_Room_Ready
A1: Data Room Readiness — Investor Due Diligence
A3: Category | B3: Document / Evidence | C3: Owner | D3: Status | E3: Priority | F3: Notes
A4: Corporate | B4: Certificate of Incorporation | C4: Founder | D4: Pending | E4: High | F4: Upload latest signed copy
A5: Corporate | B5: Cap Table (fully diluted) | C5: Founder | D5: Pending | E5: High | F5: Include options and notes
A6: Finance | B6: 3-year Financial Model (this workbook) | C6: Finance | D6: Done | E6: High | F6: Linked assumptions included
A7: Finance | B7: Bank Statements (last 12 months) | C7: Finance | D7: Pending | E7: Medium | F7: Mask sensitive account numbers
A8: Legal | B8: Terms of Service + Privacy Policy | C8: Legal | D8: Pending | E8: High | F8: GDPR alignment required
A9: Legal | B9: IP Assignment Agreements | C9: Legal | D9: Pending | E9: High | F9: Founders + contractors
A10: Product | B10: Architecture Overview | C10: CTO | D10: Done | E10: Medium | F10: Include Ocean Core + Excel Core
A11: Product | B11: Roadmap (12-18 months) | C11: Product | D11: Pending | E11: Medium | F11: Milestones + dependencies
A12: Security | B12: Security Policy + Incident Plan | C12: Security | D12: Pending | E12: High | F12: Add RTO/RPO targets
A13: Security | B13: Access Control Matrix | C13: Security | D13: Pending | E13: Medium | F13: Roles and privileges
A14: Traction | B14: User Growth Evidence | C14: Growth | D14: Done | E14: High | F14: Use product analytics exports
... A19: Operations | B19: Backup & Disaster Recovery Proof | C19: Ops | D19: Pending | E19: High | F19: Restore test evidence
A22: Completion KPIs
A23: Total Items | B23: =COUNTA(A4:A200) | D23: High Priority Open | E23: =COUNTIFS(E4:E200,"High",D4:D200,"Pending")
A24: Completed (Done) | B24: =COUNTIF(D4:D200,"Done") | D24: Medium Priority Open | E24: =COUNTIFS(E4:E200,"Medium",D4:D200,"Pending")
A25: Pending | B25: =COUNTIF(D4:D200,"Pending")
A26: Readiness % | B26: =IF(B23=0,0,B24/B23)

Sheet Dashboard
A1: Clisonix Investor Analytics Dashboard
A3: Metric | B3: 2026 | C3: 2027 | D3: 2028
A4: Revenue | B4: =PnL_3Y!B2 | C4: =PnL_3Y!C2 | D4: =PnL_3Y!D2
A5: Expenses | B5: =PnL_3Y!B3 | C5: =PnL_3Y!C3 | D5: =PnL_3Y!D3
A6: EBITDA | B6: =PnL_3Y!B4 | C6: =PnL_3Y!C4 | D6: =PnL_3Y!D4
A7: EBITDA Margin | B7: =PnL_3Y!B5 | C7: =PnL_3Y!C5 | D7: =PnL_3Y!D5
A8: Paid Users | B8: =Assumptions!B5 | C8: =Assumptions!C5 | D8: =Assumptions!D5
A9: ARPU | B9: =Assumptions!B6 | C9: =Assumptions!C6 | D9: =Assumptions!D6
